<annotation>
	<folder>eur010</folder>
	<filename>eur010_imagesq=tbnANd9GcScnYDXObRJucHNDgENUJAz31l2SVLvERgsujoU0jY56LYCfFzskw.jpg</filename>
	<path>/home/ramon/Downloads/hackathon/eur010/imagesq=tbnANd9GcScnYDXObRJucHNDgENUJAz31l2SVLvERgsujoU0jY56LYCfFzskw.jpg</path>
	<source>
		<database>Unknown</database>
	</source>
	<size>
		<width>250</width>
		<height>202</height>
		<depth>3</depth>
	</size>
	<segmented>0</segmented>
	<object>
		<name>10</name>
		<pose>Unspecified</pose>
		<truncated>1</truncated>
		<difficult>0</difficult>
		<bndbox>
			<xmin>1</xmin>
			<ymin>29</ymin>
			<xmax>150</xmax>
			<ymax>107</ymax>
		</bndbox>
	</object>
	<object>
		<name>10</name>
		<pose>Unspecified</pose>
		<truncated>0</truncated>
		<difficult>0</difficult>
		<bndbox>
			<xmin>3</xmin>
			<ymin>112</ymin>
			<xmax>150</xmax>
			<ymax>194</ymax>
		</bndbox>
	</object>
</annotation>
